README.rst
setup.py
wtforms_tornado/__init__.py
wtforms_tornado/form.py
wtforms_tornado/i18n.py
wtforms_tornado.egg-info/PKG-INFO
wtforms_tornado.egg-info/SOURCES.txt
wtforms_tornado.egg-info/dependency_links.txt
wtforms_tornado.egg-info/requires.txt
wtforms_tornado.egg-info/top_level.txt