Metadata-Version: 1.1
Name: wtforms-tornado
Version: 0.0.2
Summary: WTForms extensions for Tornado.
Home-page: https://github.com/puentesarrin/wtforms-tornado
Author: Jorge Puente Sarrín
Author-email: puentesarrin@gmail.com
License: Apache License, Version 2.0
Keywords: wtforms,tornado,validation
Platform: UNKNOWN
Classifier: Development Status :: 4 - Beta
Classifier: Intended Audience :: Developers
Classifier: License :: OSI Approved :: Apache Software License
Classifier: Operating System :: OS Independent
Classifier: Programming Language :: Python
Classifier: Programming Language :: Python :: 2.6
Classifier: Programming Language :: Python :: 2.7
Classifier: Programming Language :: Python :: 3
Classifier: Programming Language :: Python :: 3.2
Classifier: Programming Language :: Python :: 3.3
Classifier: Topic :: Internet :: WWW/HTTP :: Dynamic Content
Classifier: Topic :: Software Development :: Libraries :: Python Modules
